{
  "version": 1,
  "package": "numerics-sundials",
  "source": "doc/numerics-sundials.md",
  "symbols": {
    "np_cvode": {
      "type": "Function",
      "signature": "np_cvode(f_func, y0, tspan, rtol, atol, method, max_steps)",
      "summary": "",
      "body_md": "",
      "examples": [],
      "see_also": [],
      "section": "Definitions for numerics-sundials"
    },
    "np_cvode_close": {
      "type": "Function",
      "signature": "np_cvode_close(handle)",
      "summary": "",
      "body_md": "",
      "examples": [],
      "see_also": [],
      "section": "Definitions for numerics-sundials"
    },
    "np_cvode_create": {
      "type": "Function",
      "signature": "np_cvode_create(f, vars, y0, t0, ...)",
      "summary": "",
      "body_md": "",
      "examples": [],
      "see_also": [],
      "section": "Definitions for numerics-sundials"
    },
    "np_cvode_reinit": {
      "type": "Function",
      "signature": "np_cvode_reinit(handle, t_new, y_new)",
      "summary": "",
      "body_md": "",
      "examples": [],
      "see_also": [],
      "section": "Definitions for numerics-sundials"
    },
    "np_cvode_step": {
      "type": "Function",
      "signature": "np_cvode_step(handle, t_target)",
      "summary": "",
      "body_md": "",
      "examples": [],
      "see_also": [],
      "section": "Definitions for numerics-sundials"
    },
    "np_cvode_with_handle": {
      "type": "Function",
      "signature": "np_cvode_with_handle(create_args, body_fn)",
      "summary": "Integrate a system of ODEs dy/dt = f(t, y) using the SUNDIALS CVODE solver. Supports two calling conventions:",
      "body_md": "Integrate a system of ODEs `dy/dt = f(t, y)` using the SUNDIALS CVODE solver. Supports two calling conventions:\n\n**Expression mode:**\n- `f` — `[f1, f2, ...]` list of right-hand-side expressions for each equation\n- `vars` — `[t, y1, y2, ...]` the independent variable (time) first, then state variables\n- `y0` — initial conditions (ndarray or Maxima list)\n- `tspan` — output times (ndarray or Maxima list)\n\n**Function mode:**\n- `f_func` — function `f(t, y)` taking scalar `t` and 1D ndarray `y`, returning a Maxima list of derivatives\n- `y0` — initial conditions (ndarray or Maxima list; length determines `neq`)\n- `tspan` — output times (ndarray or Maxima list)\n\n**Common optional arguments:**\n- `rtol` — relative tolerance (default: `1e-8`)\n- `atol` — absolute tolerance (default: `1e-8`)\n- `method` — `adams` (default, non-stiff) or `bdf` (stiff systems)\n- `max_steps` — maximum internal steps between output times (default: `5000`)\n\n**Event detection (expression mode only):**\n- `events` — `[g1, g2, ...]` list of event expressions in the same variables as `f`. The solver detects zero crossings of each `g_i(t, y)` during integration.\n- `rootdir` — optional list of `-1`, `0`, `+1` (one per event) selecting the crossing direction CVODE should detect. `-1` means \"falling crossings only\" (`g_i` goes from positive to negative), `+1` means \"rising only\", `0` (the default) detects either direction. Lets you suppress a class of spurious events without filtering in user code — the natural fix for the bouncing-ball-style \"post-reset state sits exactly on the boundary\" problem.\n\n**Returns:**\n\nWithout events: a 2D ndarray of shape `[n_times, 1 + neq]` where column 0 is time and columns 1 through `neq` are state variables. The first row is the initial condition.\n\nWith events: a Maxima list `[trajectory, events_list]` where:\n- `trajectory` is the 2D ndarray as above\n- `events_list` is a list of `[t_event, [y1, ..., yn], [idx1, ...], [dir1, ...]]` entries, one per detected zero crossing. Each entry contains the event time, the state at that time, the indices (0-based) of the event expressions that triggered, and the direction (`+1` rising, `-1` falling) of each fired root in the same order as the indices.\n\nIf events are requested but none are detected, `events_list` is empty: `[trajectory, []]`.\n\n#### Stateful API: persistent CVODE handles\n\n`np_cvode` is single-shot — every call builds a fresh `cvode_mem`, integrates, and tears down. For event-driven loops (bouncing ball, switched dynamics, hybrid controllers) the consumer pays the setup cost on every segment, even though only the initial state changes between them. SUNDIALS' `CVodeReInit` is designed for exactly this — keep the integrator alive, just reset the IC. The stateful API exposes it:\n\n```maxima\nhandle : np_cvode_create(f, vars, y0, t0, rtol, atol, method, events, max_steps, rootdir)$\n[t_actual, y_state, events_during_step] : np_cvode_step(handle, t_target)$\nnp_cvode_reinit(handle, t_new, y_new)$\n[t2, y2, evs2] : np_cvode_step(handle, next_target)$\nnp_cvode_close(handle)$\n```\n\nEach `np_cvode_step` call advances the integrator from its current internal state up to `t_target`, collecting any events along the way. `np_cvode_reinit` discards the multistep history (correct after a discrete state change) and resets the IC without rebuilding the linear solver or reregistering events.\n\nResource lifecycle is two-tiered:\n\n- **Explicit close** (`np_cvode_close`) — frees the foreign resources immediately. Recommended for hot loops or long-lived sessions.\n- **GC fallback** — every handle returned by `np_cvode_create` is wrapped in a struct with a finalizer registered via `trivial-garbage`. If the user drops the reference without calling `np_cvode_close`, the finalizer runs at the next full GC and reclaims the resources. Idempotent with explicit close, so calling close + later GC is safe.\n- **`np_cvode_with_handle`** — the canonical resource-safe pattern. Wraps `create + body + close` in Common Lisp's `unwind-protect`, so the handle is always closed even if `body` errors. Maxima's own `unwind_protect` has historically been unreliable for this; the wrapper sidesteps that.\n\n```maxima\nresult : np_cvode_with_handle(\n  [f, vars, y0, t0, rtol, atol, method, events, max_steps, rootdir],\n  lambda([h],\n    /* use h freely; do whatever */\n    final_value))$\n/* h is closed by the time we get here, success or failure */\n```\n\n`np_cvode_step` returns `[t_actual, [y...], events_list]` where `events_list` has the same shape as the events list returned by `np_cvode` (entries of `[t_event, [y...], [indices], [directions]]`).\n\n#### Examples\n\nExponential decay `dy/dt = -y`, `y(0) = 1` (exact solution: `y(t) = exp(-t)`):\n\n```maxima\n(%i1) tspan : np_linspace(0.0, 2.0, 5)$\n(%i2) result : np_cvode([-y], [t, y], [1.0], tspan);\n(%o2)            ndarray([5, 2], DOUBLE-FLOAT)\n(%i3) np_ref(result, 2, 1);  /* y(1.0) ≈ exp(-1) */\n(%o3)                   0.36787944117144233\n```\n\nHarmonic oscillator `dx/dt = v`, `dv/dt = -x`:\n\n```maxima\n(%i1) tspan : np_linspace(0.0, 4.0, 41)$\n(%i2) result : np_cvode([v, -x], [t, x, v], [1.0, 0.0], tspan);\n(%o2)            ndarray([41, 3], DOUBLE-FLOAT)\n```\n\nStiff system with BDF method:\n\n```maxima\n(%i1) result : np_cvode([-50*y], [t, y], [1.0],\n                          [0.0, 0.1, 0.5, 1.0],\n                          1e-8, 1e-8, bdf);\n(%o1)            ndarray([4, 2], DOUBLE-FLOAT)\n```\n\nFunction mode:\n\n```maxima\n(%i1) f(t, y) := [-np_ref(y, 0)]$\n(%i2) result : np_cvode(f, [1.0], [0.0, 0.5, 1.0, 1.5, 2.0]);\n(%o2)            ndarray([5, 2], DOUBLE-FLOAT)\n```\n\nEvent detection — bouncing ball. Detects when height `y1` crosses zero:\n\n```maxima\n(%i1) /* dy1/dt = y2 (velocity), dy2/dt = -9.81 (gravity) */\n      result : np_cvode([y2, -9.81], [t, y1, y2],\n                         [10.0, 0.0],\n                         np_linspace(0.0, 5.0, 100),\n                         1e-8, 1e-8, adams,\n                         [y1]);\n(%o1)                 [ndarray(...), [[1.428..., [0.0, -14.01...], [0]]]]\n(%i2) traj : first(result)$\n(%i3) evs : second(result)$\n(%i4) first(first(evs));  /* time of impact */\n(%o4)                   1.4278431229...\n```\n\nMulti-bounce with coefficient of restitution:\n\n```maxima\n(%i1) traj_all : np_zeros([0, 3])$\n(%i2) y_state : [10.0, 0.0]$\n(%i3) for bounce : 1 thru 5 do (\n        sol : np_cvode([y2, -9.81], [t, y1, y2],\n                        y_state, np_linspace(0.0, 10.0, 200),\n                        1e-8, 1e-8, adams, [y1]),\n        seg : first(sol),\n        evs : second(sol),\n        if length(evs) > 0 then (\n          ev : first(evs),\n          y_state : [0.0, -0.8 * third(ev)[2]]\n        )\n      )$\n```\n\n**Performance notes:**\n\nExpression mode compiles the RHS into native Lisp closures via `coerce-float-fun`. CVODE calls these closures through a CFFI trampoline with no Maxima evaluator involvement. Function mode routes each RHS call through the Maxima evaluator.\n\nCompared to `np_odeint` (ODEPACK/DLSODE), `np_cvode` offers:\n- Variable-order methods (orders 1-12 for Adams, 1-5 for BDF) vs fixed-order\n- Built-in event detection (rootfinding) — not available in `np_odeint`\n- Automatic step-size control with the same tolerance interface\n\nSee also: `np_odeint` (ODEPACK solver in numerics-integrate)",
      "examples": [
        {
          "input": "handle : np_cvode_create(f, vars, y0, t0, rtol, atol, method, events, max_steps, rootdir)$\n[t_actual, y_state, events_during_step] : np_cvode_step(handle, t_target)$\nnp_cvode_reinit(handle, t_new, y_new)$\n[t2, y2, evs2] : np_cvode_step(handle, next_target)$\nnp_cvode_close(handle)$",
          "output": ""
        },
        {
          "input": "result : np_cvode_with_handle(\n  [f, vars, y0, t0, rtol, atol, method, events, max_steps, rootdir],\n  lambda([h],\n    /* use h freely; do whatever */\n    final_value))$\n/* h is closed by the time we get here, success or failure */",
          "output": ""
        },
        {
          "input": "tspan : np_linspace(0.0, 2.0, 5)$",
          "output": ""
        },
        {
          "input": "result : np_cvode([-y], [t, y], [1.0], tspan);",
          "output": "ndarray([5, 2], DOUBLE-FLOAT)"
        },
        {
          "input": "np_ref(result, 2, 1);  /* y(1.0) ≈ exp(-1) */",
          "output": "0.36787944117144233"
        },
        {
          "input": "tspan : np_linspace(0.0, 4.0, 41)$",
          "output": ""
        },
        {
          "input": "result : np_cvode([v, -x], [t, x, v], [1.0, 0.0], tspan);",
          "output": "ndarray([41, 3], DOUBLE-FLOAT)"
        },
        {
          "input": "result : np_cvode([-50*y], [t, y], [1.0],\n                          [0.0, 0.1, 0.5, 1.0],\n                          1e-8, 1e-8, bdf);",
          "output": "ndarray([4, 2], DOUBLE-FLOAT)"
        },
        {
          "input": "f(t, y) := [-np_ref(y, 0)]$",
          "output": ""
        },
        {
          "input": "result : np_cvode(f, [1.0], [0.0, 0.5, 1.0, 1.5, 2.0]);",
          "output": "ndarray([5, 2], DOUBLE-FLOAT)"
        },
        {
          "input": "/* dy1/dt = y2 (velocity), dy2/dt = -9.81 (gravity) */\n      result : np_cvode([y2, -9.81], [t, y1, y2],\n                         [10.0, 0.0],\n                         np_linspace(0.0, 5.0, 100),\n                         1e-8, 1e-8, adams,\n                         [y1]);",
          "output": "[ndarray(...), [[1.428..., [0.0, -14.01...], [0]]]]"
        },
        {
          "input": "traj : first(result)$",
          "output": ""
        },
        {
          "input": "evs : second(result)$",
          "output": ""
        },
        {
          "input": "first(first(evs));  /* time of impact */",
          "output": "1.4278431229..."
        },
        {
          "input": "traj_all : np_zeros([0, 3])$",
          "output": ""
        },
        {
          "input": "y_state : [10.0, 0.0]$",
          "output": ""
        },
        {
          "input": "for bounce : 1 thru 5 do (\n        sol : np_cvode([y2, -9.81], [t, y1, y2],\n                        y_state, np_linspace(0.0, 10.0, 200),\n                        1e-8, 1e-8, adams, [y1]),\n        seg : first(sol),\n        evs : second(sol),\n        if length(evs) > 0 then (\n          ev : first(evs),\n          y_state : [0.0, -0.8 * third(ev)[2]]\n        )\n      )$",
          "output": ""
        }
      ],
      "see_also": [
        "np_odeint"
      ],
      "section": "Definitions for numerics-sundials"
    }
  },
  "sections": [
    {
      "title": "Introduction",
      "body_md": "SUNDIALS CVODE integration for [maxima-numerics](https://github.com/cmsd2/maxima-numerics). Provides production-grade ODE solving via the [SUNDIALS](https://computing.llnl.gov/projects/sundials) library from Lawrence Livermore National Laboratory.\n\nFeatures:\n\n- **CVODE solver** — variable-order Adams (non-stiff) and BDF (stiff) methods\n- **Event detection** — zero-crossing rootfinding during integration\n- **Two calling modes** — expression mode (symbolic RHS) and function mode (callable RHS), matching the `np_odeint` conventions\n\n### Prerequisites\n\nSUNDIALS v6.0+ must be installed on your system:\n\n```\nmacOS:   brew install sundials\nDebian:  sudo apt install libsundials-dev\nFedora:  sudo dnf install sundials-devel\nWindows: vcpkg install sundials\n```\n\n### Loading\n\n```maxima\n(%i1) load(\"numerics\")$\n(%i2) load(\"numerics-sundials\")$\n```"
    },
    {
      "title": "Definitions for numerics-sundials",
      "body_md": ""
    }
  ]
}